{
	"format_version": "1.10.0",
	"minecraft:client_entity": {
		"description": {
			"identifier": "poke:cobalt_golem",
			"materials": {
				"default": "entity_alphatest"
			},
			"textures": {
				"default": "textures/poke/pfe/cobalt_golem_entity"
			},
			"geometry": {
				"default": "geometry.poke_pfe.cobalt_golem"
			},
			"animations": {
				"walk": "animation.cobalt_golem.walking",
				"idle": "animation.cobalt_golem.look_around",
				"walk_control": "controller.animation.cobalt_golem.walk",
				"pfe_entity_spawned": "animation.poke_pfe.cobalt_golem.spawn"
			},
			"render_controllers": [
				"controller.render.poke_pfe.default"
			],
			"scripts": {
				"animate": [
					"pfe_entity_spawned",
					"walk_control"
				]
			},
			"spawn_egg": {
				"texture": "poke_pfe_cobalt_golem_spawn_egg"
			}
		}
	}
}