{
	"format_version": "1.8.0",
	"minecraft:client_entity": {
		"description": {
			"identifier": "poke:warped_sporecat",
			"materials": {
				"default": "cat"
			},
			"textures": {
				"white": "textures/poke/pfe/sporecat_soul_entity",
				"red": "textures/poke/pfe/sporecat_crimson_entity",
				"siamese": "textures/poke/pfe/sporecat_warped_entity",
				"persian": "textures/poke/pfe/sporecat_wastes_entity",
				"calico": "textures/poke/pfe/sporecat_basalt_entity",
				"white_tame": "textures/poke/pfe/sporecat_soul_tame_entity",
				"red_tame": "textures/poke/pfe/sporecat_crimson_tame_entity",
				"siamese_tame": "textures/poke/pfe/sporecat_warped_tame_entity",
				"calico_tame": "textures/poke/pfe/sporecat_basalt_tame_entity",
				"persian_tame": "textures/poke/pfe/sporecat_wastes_tame_entity",
				"bella": "textures/poke/pfe/sporecat_bella_entity",
				"bella_tame": "textures/poke/pfe/sporecat_bella_tame_entity"
			},
			"geometry": {
				"default": "geometry.poke_pfe.sporecat"
			},
			"animations": {
				"sneak": "animation.warped_sporecat.sneak",
				"walk": "animation.warped_sporecat.walk",
				"sprint": "animation.warped_sporecat.sprint",
				"sit": "animation.warped_sporecat.sit",
				"look_at_target": "animation.common.look_at_target",
				"baby_transform": "animation.warped_sporecat.baby_transform",
				"lie_down": "animation.warped_sporecat.lie_down"
			},
			"animation_controllers": [
				{
					"look_at_target": "controller.animation.cat.look_at_target"
				},
				{
					"move": "controller.animation.cat.move"
				},
				{
					"baby": "controller.animation.cat.baby"
				}
			],
			"render_controllers": [
				"controller.render.poke_pfe.sporecat"
			],
			"spawn_egg": {
				"texture": "poke_pfe_sporecat_spawn_egg"
			}
		}
	}
}