{
	"format_version": "1.21.100",
	"minecraft:block": {
		"description": {
			"identifier": "poke:demonic_block",
			"menu_category": {
				"category": "construction"
			}
		},
		"components": {
			"minecraft:display_name": "%poke_pfe.demonic_block\n%poke_pfe.tag",
			"minecraft:material_instances": {
				"*": {
					"texture": "poke_pfe_demonic_block",
					"render_method": "opaque"
				}
			},
			"minecraft:geometry": {
				"identifier": "minecraft:geometry.full_block"
			},
			"minecraft:redstone_conductivity": {
				"redstone_conductor": true,
				"allows_wire_to_step_down": true
			},
			"minecraft:destructible_by_mining": {
				"seconds_to_destroy": 7.5,
				"item_specific_speeds": [
					{
						"item": {
							"tags": "q.any_tag('minecraft:is_pickaxe')"
						},
						"destroy_speed": 1.15
					}
				]
			},
			"minecraft:destructible_by_explosion": {
				"explosion_resistance": 30
			},
			"minecraft:map_color": "#330e09",
			"tag:pfe": {},
			"tag:metal": {},
			"tag:minecraft:metal": {},
			"tag:stone_pick_diggable": {},
			"tag:minecraft:is_pickaxe_item_destructible": {}
		}
	}
}