{
	"format_version": "1.21.110",
	"minecraft:item": {
		"description": {
			"identifier": "poke:maxwell",
			"menu_category": {
				"category": "equipment"
			}
		},
		"components": {
			"minecraft:display_name": {
				"value": "%poke_pfe.maxwell\nยง7%poke_pfe.offhand_cosmetic\n%poke_pfe.tag"
			},
			"minecraft:rarity": "common",
			"minecraft:tags": {
				"tags": [
					"novelty:is_hat"
				]
			},
			"minecraft:max_stack_size": 1,
			"minecraft:icon": {
				"textures": {
					"default": "poke_pfe_maxwell"
				}
			},
			"minecraft:wearable": {
				"slot": "slot.weapon.offhand"
			}
		}
	}
}