{
	"format_version": "1.21.90",
	"minecraft:item": {
		"description": {
			"identifier": "poke:hellish_arrow",
			"menu_category": {
				"category": "equipment"
			}
		},
		"components": {
			"minecraft:display_name": {
				"value": "%poke_pfe.hellish_arrow\n%poke_pfe.tag"
			},
			"minecraft:max_stack_size": 64,
			"minecraft:icon": "poke_pfe_hellish_arrow",
			"minecraft:projectile": {
				"projectile_entity": "poke:hellish_arrow",
				"minimum_critical_power": 0.5
			},
			"minecraft:allow_off_hand": {
				"value": true
			},
			"minecraft:tags": {
				"tags": [
					"minecraft:arrow"
				]
			}
		}
	}
}